vk_facenet/__init__.py
vk_facenet/calculate_filtering_metrics.py
vk_facenet/classifier.py
vk_facenet/compare.py
vk_facenet/decode_msceleb_dataset.py
vk_facenet/download_and_extract.py
vk_facenet/facenet.py
vk_facenet/freeze_graph.py
vk_facenet/lfw.py
vk_facenet/train_softmax.py
vk_facenet/train_tripletloss.py
vk_facenet/validate_on_lfw.py
vk_facenet/align/__init__.py
vk_facenet/align/align_dataset_mtcnn.py
vk_facenet/align/det1.npy
vk_facenet/align/det2.npy
vk_facenet/align/det3.npy
vk_facenet/align/detect_face.py
vk_facenet/generative/__init__.py
vk_facenet/generative/calculate_attribute_vectors.py
vk_facenet/generative/calculate_dataset_normalization.py
vk_facenet/generative/modify_attribute.py
vk_facenet/generative/train_vae.py
vk_facenet/generative/models/__init__.py
vk_facenet/generative/models/dfc_vae.py
vk_facenet/generative/models/dfc_vae_large.py
vk_facenet/generative/models/dfc_vae_resnet.py
vk_facenet/generative/models/vae_base.py
vk_facenet/models/__init__.py
vk_facenet/models/dummy.py
vk_facenet/models/inception_resnet_v1.py
vk_facenet/models/inception_resnet_v2.py
vk_facenet/models/squeezenet.py
vk_facenet-1.1.0.dist-info/DESCRIPTION.rst
vk_facenet-1.1.0.dist-info/METADATA
vk_facenet-1.1.0.dist-info/RECORD
vk_facenet-1.1.0.dist-info/WHEEL
vk_facenet-1.1.0.dist-info/metadata.json
vk_facenet-1.1.0.dist-info/top_level.txt
