Metadata-Version: 2.0
Name: vk-facenet
Version: 1.1.0
Summary: facenet
Home-page: https://github.com/pypa/sampleproject
Author: lijinchao2007
Author-email: lijinchao2007@163.com
License: MIT License
Keywords: pip,vanke,facenet
Platform: any
Requires-Dist: tensorflow
Requires-Dist: scipy
